hanpinyin/__init__.py
hanpinyin/bert-base-chinese_s2t_dict.txt
hanpinyin/bopomofo_to_pinyin_wo_tune_dict.json
hanpinyin/char_bopomofo_dict.json
hanpinyin/g2pw.py
hanpinyin/torch_infer_api.py
hanpinyin-0.1.0.dist-info/LICENSE
hanpinyin-0.1.0.dist-info/METADATA
hanpinyin-0.1.0.dist-info/WHEEL
hanpinyin-0.1.0.dist-info/top_level.txt
hanpinyin-0.1.0.dist-info/RECORD
