Metadata-Version: 2.1
Name: hanpinyin
Version: 0.1.0
Summary: 基于 g2pW 使用 torch 推理的 pypinyin
Author: He Mingze
Author-email: hhhhmdzz1024@gmail.com
Classifier: Programming Language :: Python :: 3
Classifier: License :: OSI Approved :: MIT License
Classifier: Operating System :: OS Independent
Requires-Python: >=3.6, <4
License-File: LICENSE
Requires-Dist: g2pw >=0.1.1
Requires-Dist: pypinyin >=0.47.1
